Pylibft/__init__.py
Pylibft/base_convert.py
Pylibft/bin2hex.py
Pylibft/hex2bin.py
Pylibft/print_message.py
Pylibft-0.0.3.dist-info/LICENSE
Pylibft-0.0.3.dist-info/METADATA
Pylibft-0.0.3.dist-info/WHEEL
Pylibft-0.0.3.dist-info/top_level.txt
Pylibft-0.0.3.dist-info/RECORD
