Metadata-Version: 2.1
Name: Pylibft
Version: 0.0.3
Summary: You can find here some functions that can help you during the automation in CTF/Pentest.
Home-page: UNKNOWN
Author: Wiloti
Author-email: contact@wiloti.fr
License: UNKNOWN
Keywords: python,CTF,Pentest,automation
Platform: UNKNOWN
Classifier: Intended Audience :: Developers
Classifier: Programming Language :: Python :: 3
Classifier: Operating System :: Unix
Classifier: Operating System :: Microsoft :: Windows
Requires-Dist: termcolor
Requires-Dist: typing-extensions
